muffinbite/__init__.py
muffinbite/commands/__init__.py
muffinbite/commands/build.py
muffinbite/commands/campaign.py
muffinbite/commands/configure.py
muffinbite/commands/quit.py
muffinbite/commands/reset_config.py
muffinbite/commands/send.py
muffinbite/esp/__init__.py
muffinbite/esp/google_esp.py
muffinbite/esp/smtp_esp.py
muffinbite/management/__init__.py
muffinbite/management/cli.py
muffinbite/management/session_watcher.py
muffinbite/management/settings.py
muffinbite/sender/__init__.py
muffinbite/sender/sender.py
muffinbite/utils/__init__.py
muffinbite/utils/abstracts.py
muffinbite/utils/helpers.py
muffinbite/utils/hybridcompleter.py
muffinbite-0.1.14.dist-info/licenses/LICENSE
muffinbite-0.1.14.dist-info/METADATA
muffinbite-0.1.14.dist-info/WHEEL
muffinbite-0.1.14.dist-info/entry_points.txt
muffinbite-0.1.14.dist-info/top_level.txt
muffinbite-0.1.14.dist-info/RECORD
