Metadata-Version: 2.4
Name: muffinbite
Version: 0.1.14
Summary: Interactive Python CLI tool for sending personalized bulk emails via Gmail API or SMTP with explicit user-triggered execution
Home-page: https://www.muffinbite.dev/
Author: Shivansh Varshney
Author-email: shivanshvarshney45@gmail.com
License: MIT
Project-URL: Github, https://github.com/Shivansh-varshney/MuffinBite
Project-URL: Maintainer, https://www.shivanshvarshney.tech/
Keywords: email,cli,bulk-email,gmail-api,smtp,campaigns
Classifier: Programming Language :: Python :: 3.10
Classifier: Programming Language :: Python :: 3.11
Classifier: Programming Language :: Python :: 3.12
Classifier: Operating System :: POSIX :: Linux
Classifier: Operating System :: Microsoft :: Windows
Classifier: Operating System :: MacOS
Classifier: Environment :: Console
Classifier: Topic :: Communications :: Email
Classifier: Topic :: Utilities
Requires-Python: >=3.10, <3.13
License-File: LICENSE
Requires-Dist: beautifulsoup4==4.13.5
Requires-Dist: build==1.3.0
Requires-Dist: cachetools==5.5.2
Requires-Dist: certifi==2025.1.31
Requires-Dist: cffi==2.0.0
Requires-Dist: charset-normalizer==3.4.1
Requires-Dist: colorama==0.4.6
Requires-Dist: configparser==7.2.0
Requires-Dist: cryptography==45.0.7
Requires-Dist: docutils==0.22.2
Requires-Dist: et_xmlfile==2.0.0
Requires-Dist: google-api-core==2.24.2
Requires-Dist: google-api-python-client==2.167.0
Requires-Dist: google-auth==2.39.0
Requires-Dist: google-auth-httplib2==0.2.0
Requires-Dist: google-auth-oauthlib==1.2.1
Requires-Dist: googleapis-common-protos==1.70.0
Requires-Dist: httplib2==0.22.0
Requires-Dist: id==1.5.0
Requires-Dist: idna==3.10
Requires-Dist: jaraco.classes==3.4.0
Requires-Dist: jaraco.context==6.0.1
Requires-Dist: jaraco.functools==4.3.0
Requires-Dist: jeepney==0.9.0
Requires-Dist: keyring==25.6.0
Requires-Dist: markdown-it-py==4.0.0
Requires-Dist: mdurl==0.1.2
Requires-Dist: more-itertools==10.8.0
Requires-Dist: nh3==0.3.1
Requires-Dist: numpy==2.2.4
Requires-Dist: oauthlib==3.2.2
Requires-Dist: openpyxl==3.1.5
Requires-Dist: packaging==25.0
Requires-Dist: pandas==2.2.3
Requires-Dist: plyer==2.1.0
Requires-Dist: prettytable==3.16.0
Requires-Dist: prompt_toolkit==3.0.52
Requires-Dist: proto-plus==1.26.1
Requires-Dist: protobuf==6.30.2
Requires-Dist: pwinput==1.0.3
Requires-Dist: pyasn1==0.6.1
Requires-Dist: pyasn1_modules==0.4.2
Requires-Dist: pycparser==2.23
Requires-Dist: Pygments==2.19.2
Requires-Dist: pyparsing==3.2.3
Requires-Dist: pyproject_hooks==1.2.0
Requires-Dist: python-dateutil==2.9.0.post0
Requires-Dist: pytz==2025.2
Requires-Dist: readme_renderer==44.0
Requires-Dist: requests==2.32.3
Requires-Dist: requests-oauthlib==2.0.0
Requires-Dist: requests-toolbelt==1.0.0
Requires-Dist: rfc3986==2.0.0
Requires-Dist: rich==14.2.0
Requires-Dist: rsa==4.9.1
Requires-Dist: SecretStorage==3.4.0
Requires-Dist: setuptools==80.9.0
Requires-Dist: six==1.17.0
Requires-Dist: soupsieve==2.8
Requires-Dist: twine==6.2.0
Requires-Dist: typing_extensions==4.15.0
Requires-Dist: tzdata==2025.2
Requires-Dist: uritemplate==4.1.1
Requires-Dist: urllib3==2.4.0
Requires-Dist: watchdog==6.0.0
Requires-Dist: wcwidth==0.2.13
Requires-Dist: wheel==0.45.1
Dynamic: author
Dynamic: author-email
Dynamic: classifier
Dynamic: description
Dynamic: description-content-type
Dynamic: home-page
Dynamic: keywords
Dynamic: license
Dynamic: license-file
Dynamic: project-url
Dynamic: requires-dist
Dynamic: requires-python
Dynamic: summary
